{
"type": "FeatureCollection",
"crs": { "type": "name", "properties": { "name": "urn:ogc:def:crs:OGC:1.3:CRS84" } },
                                                                                
"features": [
{ "type": "Feature", "properties": { "cat": 1 }, "geometry": { "type": "Point", "coordinates": [ -84.13735114, 9.91929813 ] } },
{ "type": "Feature", "properties": { "cat": 2 }, "geometry": { "type": "Point", "coordinates": [ -84.13819151, 9.92048292 ] } },
{ "type": "Feature", "id": -1294967293, "properties": { "cat": 3 }, "geometry": { "type": "Point", "coordinates": [ -84.13872879, 9.92107531 ] } },
{ "type": "Feature", "id": -294967292, "properties": { "cat": 4 }, "geometry": { "type": "Point", "coordinates": [ -84.13915587, 9.91851287 ] } },
{ "type": "Feature", "id": 705032709, "properties": { "cat": 5 }, "geometry": { "type": "Point", "coordinates": [ -84.14090549, 9.91815468 ] } },
{ "type": "Feature", "id": 1705032710, "properties": { "cat": 6 }, "geometry": { "type": "Point", "coordinates": [ -84.14080905, 9.92038648 ] } }
]
}
